{
    "code": 0,
    "msg": "",
    "count": 30,
    "data": [
        {
            "id": 10000,
            "time": "2018-10-10 10:00:00",
            "name": "张小名",
            "score": "98",
            "level": "A"
        },
        {
            "id": 10001,
            "time": "2018-10-10 10:00:00",
            "name": "张小名",
            "score": "98",
            "level": "A"
        },
        {
            "id": 10002,
            "time": "2018-10-10 10:00:00",
            "name": "张小名",
            "score": "98",
            "level": "A"
        },
        {
            "id": 10003,
            "time": "2018-10-10 10:00:00",
            "name": "张小名",
            "score": "98",
            "level": "A"
        },
        {
            "id": 10004,
            "time": "2018-10-10 10:00:00",
            "name": "张小名",
            "score": "98",
            "level": "A"
        },
        {
            "id": 10005,
            "time": "2018-10-10 10:00:00",
            "name": "张小名",
            "score": "98",
            "level": "A"
        },
        {
            "id": 10006,
            "time": "2018-10-10 10:00:00",
            "name": "张小名",
            "score": "98",
            "level": "A"
        },
        {
            "id": 10007,
            "time": "2018-10-10 10:00:00",
            "name": "张小名",
            "score": "98",
            "level": "A"
        },
        {
            "id": 10008,
            "time": "2018-10-10 10:00:00",
            "name": "张小名",
            "score": "98",
            "level": "A"
        },
        {
            "id": 10009,
            "time": "2018-10-10 10:00:00",
            "name": "张小名",
            "score": "98",
            "level": "A"
        },
        {
            "id": 10010,
            "time": "2018-10-10 10:00:00",
            "name": "张小名",
            "score": "98",
            "level": "A"
        },
        {
            "id": 10011,
            "time": "2018-10-10 10:00:00",
            "name": "张小名",
            "score": "98",
            "level": "A"
        },
        {
            "id": 10012,
            "time": "2018-10-10 10:00:00",
            "name": "张小名",
            "score": "98",
            "level": "A"
        },
        {
            "id": 10013,
            "time": "2018-10-10 10:00:00",
            "name": "张小名",
            "score": "98",
            "level": "A"
        },
        {
            "id": 10014,
            "time": "2018-10-10 10:00:00",
            "name": "张小名",
            "score": "98",
            "level": "A"
        },
        {
            "id": 10015,
            "time": "2018-10-10 10:00:00",
            "name": "张小名",
            "score": "98",
            "level": "A"
        },
        {
            "id": 10016,
            "time": "2018-10-10 10:00:00",
            "name": "张小名",
            "score": "98",
            "level": "A"
        },
        {
            "id": 10017,
            "time": "2018-10-10 10:00:00",
            "name": "张小名",
            "score": "98",
            "level": "A"
        },
        {
            "id": 10018,
            "time": "2018-10-10 10:00:00",
            "name": "张小名",
            "score": "98",
            "level": "A"
        },
        {
            "id": 10019,
            "time": "2018-10-10 10:00:00",
            "name": "张小名",
            "score": "98",
            "level": "A"
        },
        {
            "id": 10020,
            "time": "2018-10-10 10:00:00",
            "name": "张小名",
            "score": "98",
            "level": "A"
        },
        {
            "id": 10021,
            "time": "2018-10-10 10:00:00",
            "name": "张小名",
            "score": "98",
            "level": "A"
        },
        {
            "id": 10022,
            "time": "2018-10-10 10:00:00",
            "name": "张小名",
            "score": "98",
            "level": "A"
        },
        {
            "id": 10023,
            "time": "2018-10-10 10:00:00",
            "name": "张小名",
            "score": "98",
            "level": "A"
        },
        {
            "id": 10024,
            "time": "2018-10-10 10:00:00",
            "name": "张小名",
            "score": "98",
            "level": "A"
        },
        {
            "id": 10025,
            "time": "2018-10-10 10:00:00",
            "name": "张小名",
            "score": "98",
            "level": "A"
        },
        {
            "id": 10026,
            "time": "2018-10-10 10:00:00",
            "name": "张小名",
            "score": "98",
            "level": "A"
        },
        {
            "id": 10027,
            "time": "2018-10-10 10:00:00",
            "name": "张小名",
            "score": "98",
            "level": "A"
        },
        {
            "id": 10028,
            "time": "2018-10-10 10:00:00",
            "name": "张小名",
            "score": "98",
            "level": "A"
        },
        {
            "id": 10029,
            "time": "2018-10-10 10:00:00",
            "name": "张小名",
            "score": "98",
            "level": "A"
        }
    ]
}